crispy_cookie/__init__.py
crispy_cookie/cli.py
crispy_cookie/core.py
crispy_cookie/rebase.py
crispy_cookie-0.7.3.dist-info/AUTHORS.rst
crispy_cookie-0.7.3.dist-info/LICENSE
crispy_cookie-0.7.3.dist-info/METADATA
crispy_cookie-0.7.3.dist-info/WHEEL
crispy_cookie-0.7.3.dist-info/entry_points.txt
crispy_cookie-0.7.3.dist-info/top_level.txt
crispy_cookie-0.7.3.dist-info/RECORD
