Metadata-Version: 2.1
Name: crispy-cookie
Version: 0.7.3
Summary: Splunk app boilerplate builder that uses a combination of Cookiecutter and Ksconf layers.
Home-page: https://github.com/lowell80/crispy_cookie
Author: Lowell Alleman
Author-email: lowell87@gmail.com
License: Apache Software License 2.0
Keywords: crispy_cookie
Classifier: Development Status :: 2 - Pre-Alpha
Classifier: Intended Audience :: Developers
Classifier: License :: OSI Approved :: Apache Software License
Classifier: Natural Language :: English
Classifier: Programming Language :: Python :: 3
Classifier: Programming Language :: Python :: 3.6
Classifier: Programming Language :: Python :: 3.7
Classifier: Programming Language :: Python :: 3.8
Requires-Python: >=3.6
License-File: LICENSE
License-File: AUTHORS.rst
Requires-Dist: ksconf >=0.11
Requires-Dist: cookiecutter >=1.7.1
